LICENSE
MANIFEST.in
README.md
requirements.txt
setup.cfg
setup.py
tfvan/__init__.py
tfvan/attn.py
tfvan/block.py
tfvan/drop.py
tfvan/embed.py
tfvan/mlp.py
tfvan/model.py
tfvan/norm.py
tfvan/pad.py
tfvan/prep.py
tfvan.egg-info/PKG-INFO
tfvan.egg-info/SOURCES.txt
tfvan.egg-info/dependency_links.txt
tfvan.egg-info/requires.txt
tfvan.egg-info/top_level.txt